timeline_logger/__init__.py
timeline_logger/admin.py
timeline_logger/apps.py
timeline_logger/compat.py
timeline_logger/conf.py
timeline_logger/manager.py
timeline_logger/models.py
timeline_logger/py.typed
timeline_logger/resources.py
timeline_logger/service.py
timeline_logger/urls.py
timeline_logger/views.py
timeline_logger/locale/nl/LC_MESSAGES/django.mo
timeline_logger/locale/nl/LC_MESSAGES/django.po
timeline_logger/management/__init__.py
timeline_logger/management/commands/__init__.py
timeline_logger/management/commands/prune_timeline_logs.py
timeline_logger/management/commands/report_mailing.py
timeline_logger/migrations/0001_initial.py
timeline_logger/migrations/0002_auto_20160624_1045.py
timeline_logger/migrations/0003_auto_20171025_1414.py
timeline_logger/migrations/0004_alter_fields.py
timeline_logger/migrations/0005_auto_20220413_0742.py
timeline_logger/migrations/0006_auto_20220413_0749.py
timeline_logger/migrations/__init__.py
timeline_logger/templates/timeline_logger/base.html
timeline_logger/templates/timeline_logger/created.txt
timeline_logger/templates/timeline_logger/default.txt
timeline_logger/templates/timeline_logger/notifications.html
timeline_logger/templates/timeline_logger/timelinelog_list.html
timeline_logger/templates/timeline_logger/updated.txt
timeline_logger/templatetags/__init__.py
timeline_logger/templatetags/timeline.py
django_timeline_logger-5.0.0.dist-info/LICENSE
django_timeline_logger-5.0.0.dist-info/METADATA
django_timeline_logger-5.0.0.dist-info/WHEEL
django_timeline_logger-5.0.0.dist-info/top_level.txt
django_timeline_logger-5.0.0.dist-info/RECORD
