Metadata-Version: 2.1
Name: django-timeline-logger
Version: 5.0.0
Summary: Generic event logger for Django models.
Author-email: Maykin Media <support@maykinmedia.nl>
License: The MIT License (MIT)
Project-URL: Homepage, https://github.com/maykinmedia/django-timeline-logger
Project-URL: Documentation, http://django-timeline-logger.readthedocs.io/en/latest/
Project-URL: Bug Tracker, https://github.com/maykinmedia/django-timeline-logger/issues
Project-URL: Source Code, https://github.com/maykinmedia/django-timeline-logger
Project-URL: Changelog, https://github.com/maykinmedia/django-timeline-logger/blob/master/docs/changelog.rst
Keywords: django,generic logging
Classifier: Development Status :: 5 - Production/Stable
Classifier: Framework :: Django
Classifier: Framework :: Django :: 4.2
Classifier: Intended Audience :: Developers
Classifier: Operating System :: Unix
Classifier: Operating System :: MacOS
Classifier: Operating System :: Microsoft :: Windows
Classifier: Programming Language :: Python :: 3.10
Classifier: Programming Language :: Python :: 3.11
Classifier: Programming Language :: Python :: 3.12
Classifier: Topic :: Software Development :: Libraries :: Python Modules
Requires-Python: >=3.10
License-File: LICENSE
Requires-Dist: django >=3.2
Requires-Dist: django-appconf
Provides-Extra: coverage
Requires-Dist: pytest-cov ; extra == 'coverage'
Provides-Extra: docs
Requires-Dist: sphinx ; extra == 'docs'
Requires-Dist: sphinx-rtd-theme ; extra == 'docs'
Provides-Extra: release
Requires-Dist: bump-my-version ; extra == 'release'
Requires-Dist: twine ; extra == 'release'
Provides-Extra: tests
Requires-Dist: factory-boy ; extra == 'tests'
Requires-Dist: time-machine ; extra == 'tests'
Requires-Dist: psycopg2 ; extra == 'tests'
Requires-Dist: pytest ; extra == 'tests'
Requires-Dist: pytest-cov ; extra == 'tests'
Requires-Dist: pytest-django ; extra == 'tests'
Requires-Dist: pytest-pep8 ; extra == 'tests'
Requires-Dist: pytest-pylint ; extra == 'tests'
Requires-Dist: pytest-pythonpath ; extra == 'tests'
Requires-Dist: pytest-runner ; extra == 'tests'
Requires-Dist: tox ; extra == 'tests'
Requires-Dist: black ; extra == 'tests'
Requires-Dist: isort ; extra == 'tests'
Requires-Dist: flake8 ; extra == 'tests'
